robotsparser/__init__.py
robotsparser/parser.py
robotsparser-0.0.12.dist-info/LICENSE
robotsparser-0.0.12.dist-info/METADATA
robotsparser-0.0.12.dist-info/WHEEL
robotsparser-0.0.12.dist-info/top_level.txt
robotsparser-0.0.12.dist-info/RECORD
