Metadata-Version: 2.1
Name: robotsparser
Version: 0.0.12
Summary: Parse robots.txt files and find indexed urls
Home-page: https://github.com/Dvelezs94/robotsparser
Author: Diego Velez
Author-email: diegovelezs94@gmail.com
Keywords: robots.txt,sitemap,crawler,data mining
Classifier: Development Status :: 1 - Planning
Classifier: Intended Audience :: Developers
Classifier: Programming Language :: Python :: 3
Classifier: Operating System :: Unix
Classifier: Operating System :: MacOS :: MacOS X
Classifier: Operating System :: Microsoft :: Windows
License-File: LICENSE
Requires-Dist: bs4
Requires-Dist: lxml
Requires-Dist: cloudscraper
